difflib_parser/__init__.py
difflib_parser/diff.py
difflib_parser/diff_change.py
difflib_parser/diff_code.py
difflib_parser/diff_line.py
difflib_parser/diff_line_code.py
difflib_parser/difflib_parser.py
difflib_parser/py.typed
difflib_parser/version.py
difflib_parser-2.1.0.dist-info/METADATA
difflib_parser-2.1.0.dist-info/WHEEL
difflib_parser-2.1.0.dist-info/licenses/LICENSE
difflib_parser-2.1.0.dist-info/RECORD
