Metadata-Version: 2.4
Name: difflib-parser
Version: 2.1.0
Summary: Lightweight Python package for parsing Python difflib's diff results
Project-URL: Homepage, https://github.com/git-mastery/difflib-parser.git
Project-URL: Repository, https://github.com/git-mastery/difflib-parser.git
Project-URL: Issues, https://github.com/git-mastery/difflib-parser/issues
Author-email: "Jiahao, Woo" <woojiahao1234@gmail.com>
License: MIT License
License-File: LICENSE
Classifier: Development Status :: 4 - Beta
Classifier: Intended Audience :: Developers
Classifier: Programming Language :: Python :: 3.13
Classifier: Topic :: Software Development
Requires-Python: >=3.13
